MANIFEST.in
README.txt
setup.py
docs/AUTHOR.txt
docs/HISTORY.txt
docs/INSTALL.txt
docs/LICENSE.txt
google/__init__.py
google.directions.egg-info/PKG-INFO
google.directions.egg-info/SOURCES.txt
google.directions.egg-info/dependency_links.txt
google.directions.egg-info/entry_points.txt
google.directions.egg-info/namespace_packages.txt
google.directions.egg-info/requires.txt
google.directions.egg-info/top_level.txt
google.directions.egg-info/zip-safe
google/directions/README.txt
google/directions/__init__.py
google/directions/gdapi.py
google/directions/test.py