Metadata-Version: 1.0
Name: google.directions
Version: 0.3
Summary: A python api to google directions
Home-page: http://d9t.de/os
Author: D9T GmbH, Daniel Kraft
Author-email: dk@d9t.de
License: GPLv3
Keywords: google directions d9t
Platform: UNKNOWN
Classifier: Programming Language :: Python
Classifier: Topic :: Software Development :: Libraries :: Python Modules
